pytest_html/__init__.py
pytest_html/extras.py
pytest_html/hooks.py
pytest_html/plugin.py
pytest_html/resources/main.js
pytest_html/resources/style.css
pytest_html_lee-0.0.1.dist-info/LICENSE
pytest_html_lee-0.0.1.dist-info/METADATA
pytest_html_lee-0.0.1.dist-info/WHEEL
pytest_html_lee-0.0.1.dist-info/entry_points.txt
pytest_html_lee-0.0.1.dist-info/top_level.txt
pytest_html_lee-0.0.1.dist-info/RECORD
